{
  "attributes": [],
  "baby_trigger_for": null,
  "category": {
    "name": "plot-advancement",
    "url": "json/item-category/0022.json"
  },
  "cost": 0,
  "effect_entries": [
    {
      "effect": "May be traded to Captain Stern for a deep sea tooth or a deep sea scale.",
      "language": {
        "name": "en",
        "url": "json/language/0009.json"
      },
      "short_effect": "Trade to Captain Stern for a DeepSeaTooth or DeepSeaScale."
    }
  ],
  "flavor_text_entries": [
    {
      "language": {
        "name": "zh-Hans",
        "url": "json/language/0012.json"
      },
      "text": "在海紫堇中\n找到的道具。",
      "version_group": {
        "name": "ultra-sun-ultra-moon",
        "url": "json/version-group/0018.json"
      }
    },
    {
      "language": {
        "name": "ja",
        "url": "json/language/0011.json"
      },
      "text": "シーキンセツの　中で\nみつけた　道具。",
      "version_group": {
        "name": "ultra-sun-ultra-moon",
        "url": "json/version-group/0018.json"
      }
    },
    {
      "language": {
        "name": "en",
        "url": "json/language/0009.json"
      },
      "text": "A device found inside Sea Mauville.",
      "version_group": {
        "name": "ultra-sun-ultra-moon",
        "url": "json/version-group/0018.json"
      }
    },
    {
      "language": {
        "name": "it",
        "url": "json/language/0008.json"
      },
      "text": "Dispositivo trovato nella scogliera artificiale\nCiclamare.",
      "version_group": {
        "name": "ultra-sun-ultra-moon",
        "url": "json/version-group/0018.json"
      }
    },
    {
      "language": {
        "name": "es",
        "url": "json/language/0007.json"
      },
      "text": "Objeto hallado en el interior de Malvamar.",
      "version_group": {
        "name": "ultra-sun-ultra-moon",
        "url": "json/version-group/0018.json"
      }
    },
    {
      "language": {
        "name": "de",
        "url": "json/language/0006.json"
      },
      "text": "Ein Gerät, das du in Seewoge Malvenfroh gefunden\nhast.",
      "version_group": {
        "name": "ultra-sun-ultra-moon",
        "url": "json/version-group/0018.json"
      }
    },
    {
      "language": {
        "name": "fr",
        "url": "json/language/0005.json"
      },
      "text": "Un objet trouvé à Lavandia Sea.",
      "version_group": {
        "name": "ultra-sun-ultra-moon",
        "url": "json/version-group/0018.json"
      }
    },
    {
      "language": {
        "name": "zh-Hant",
        "url": "json/language/0004.json"
      },
      "text": "在海紫菫中\n找到的道具。",
      "version_group": {
        "name": "ultra-sun-ultra-moon",
        "url": "json/version-group/0018.json"
      }
    },
    {
      "language": {
        "name": "ko",
        "url": "json/language/0003.json"
      },
      "text": "씨보라 안에서\n발견한 도구.",
      "version_group": {
        "name": "ultra-sun-ultra-moon",
        "url": "json/version-group/0018.json"
      }
    },
    {
      "language": {
        "name": "ja-Hrkt",
        "url": "json/language/0001.json"
      },
      "text": "シーキンセツの　なかで\nみつけた　どうぐ。",
      "version_group": {
        "name": "ultra-sun-ultra-moon",
        "url": "json/version-group/0018.json"
      }
    },
    {
      "language": {
        "name": "zh-Hans",
        "url": "json/language/0012.json"
      },
      "text": "在海紫堇中\n找到的道具。",
      "version_group": {
        "name": "sun-moon",
        "url": "json/version-group/0017.json"
      }
    },
    {
      "language": {
        "name": "ja",
        "url": "json/language/0011.json"
      },
      "text": "シーキンセツの　中で\nみつけた　道具。",
      "version_group": {
        "name": "sun-moon",
        "url": "json/version-group/0017.json"
      }
    },
    {
      "language": {
        "name": "en",
        "url": "json/language/0009.json"
      },
      "text": "A device found inside Sea Mauville.",
      "version_group": {
        "name": "sun-moon",
        "url": "json/version-group/0017.json"
      }
    },
    {
      "language": {
        "name": "it",
        "url": "json/language/0008.json"
      },
      "text": "Dispositivo trovato nella scogliera artificiale\nCiclamare.",
      "version_group": {
        "name": "sun-moon",
        "url": "json/version-group/0017.json"
      }
    },
    {
      "language": {
        "name": "es",
        "url": "json/language/0007.json"
      },
      "text": "Objeto hallado en el interior de Malvamar.",
      "version_group": {
        "name": "sun-moon",
        "url": "json/version-group/0017.json"
      }
    },
    {
      "language": {
        "name": "de",
        "url": "json/language/0006.json"
      },
      "text": "Ein Gerät, das du in Seewoge Malvenfroh gefunden\nhast.",
      "version_group": {
        "name": "sun-moon",
        "url": "json/version-group/0017.json"
      }
    },
    {
      "language": {
        "name": "fr",
        "url": "json/language/0005.json"
      },
      "text": "Un objet trouvé à Lavandia Sea.",
      "version_group": {
        "name": "sun-moon",
        "url": "json/version-group/0017.json"
      }
    },
    {
      "language": {
        "name": "zh-Hant",
        "url": "json/language/0004.json"
      },
      "text": "在海紫菫中\n找到的道具。",
      "version_group": {
        "name": "sun-moon",
        "url": "json/version-group/0017.json"
      }
    },
    {
      "language": {
        "name": "ko",
        "url": "json/language/0003.json"
      },
      "text": "씨보라 안에서\n발견한 도구.",
      "version_group": {
        "name": "sun-moon",
        "url": "json/version-group/0017.json"
      }
    },
    {
      "language": {
        "name": "ja-Hrkt",
        "url": "json/language/0001.json"
      },
      "text": "シーキンセツの　なかで\nみつけた　どうぐ。",
      "version_group": {
        "name": "sun-moon",
        "url": "json/version-group/0017.json"
      }
    },
    {
      "language": {
        "name": "en",
        "url": "json/language/0009.json"
      },
      "text": "A device used to search for\nlife-forms in water.\nIt looks too difficult to use.",
      "version_group": {
        "name": "firered-leafgreen",
        "url": "json/version-group/0007.json"
      }
    },
    {
      "language": {
        "name": "en",
        "url": "json/language/0009.json"
      },
      "text": "A device found\ninside the\nABANDONED SHIP.",
      "version_group": {
        "name": "emerald",
        "url": "json/version-group/0006.json"
      }
    },
    {
      "language": {
        "name": "en",
        "url": "json/language/0009.json"
      },
      "text": "A device found\ninside the\nABANDONED SHIP.",
      "version_group": {
        "name": "ruby-sapphire",
        "url": "json/version-group/0005.json"
      }
    }
  ],
  "fling_effect": null,
  "fling_power": null,
  "game_indices": [
    {
      "game_index": 727,
      "generation": {
        "name": "generation-vii",
        "url": "json/generation/0007.json"
      }
    },
    {
      "game_index": 278,
      "generation": {
        "name": "generation-iii",
        "url": "json/generation/0003.json"
      }
    }
  ],
  "held_by_pokemon": [],
  "id": 535,
  "machines": [],
  "name": "scanner",
  "names": [
    {
      "language": {
        "name": "zh-Hans",
        "url": "json/language/0012.json"
      },
      "name": "探测器"
    },
    {
      "language": {
        "name": "ja",
        "url": "json/language/0011.json"
      },
      "name": "たんちき"
    },
    {
      "language": {
        "name": "en",
        "url": "json/language/0009.json"
      },
      "name": "Scanner"
    },
    {
      "language": {
        "name": "it",
        "url": "json/language/0008.json"
      },
      "name": "Scanner"
    },
    {
      "language": {
        "name": "es",
        "url": "json/language/0007.json"
      },
      "name": "Escáner"
    },
    {
      "language": {
        "name": "de",
        "url": "json/language/0006.json"
      },
      "name": "Scanner"
    },
    {
      "language": {
        "name": "fr",
        "url": "json/language/0005.json"
      },
      "name": "Scanner"
    },
    {
      "language": {
        "name": "zh-Hant",
        "url": "json/language/0004.json"
      },
      "name": "探測器"
    },
    {
      "language": {
        "name": "ko",
        "url": "json/language/0003.json"
      },
      "name": "탐지기"
    },
    {
      "language": {
        "name": "ja-Hrkt",
        "url": "json/language/0001.json"
      },
      "name": "たんちき"
    }
  ],
  "sprites": {
    "default": "image/item/scanner.png"
  }
}