{
  "accuracy": 90,
  "contest_combos": {
    "normal": {
      "use_after": [
        {
          "name": "swords-dance",
          "url": "json/move/0014.json"
        },
        {
          "name": "rain-dance",
          "url": "json/move/0240.json"
        }
      ],
      "use_before": null
    },
    "super": {
      "use_after": null,
      "use_before": null
    }
  },
  "contest_effect": {
    "url": "json/contest-effect/0002.json"
  },
  "contest_type": {
    "name": "tough",
    "url": "json/contest-type/0005.json"
  },
  "damage_class": {
    "name": "physical",
    "url": "json/move-damage-class/0002.json"
  },
  "effect_chance": null,
  "effect_changes": [],
  "effect_entries": [
    {
      "effect": "Inflicts regular damage.  User's critical hit rate is one level higher when using this move.",
      "language": {
        "name": "en",
        "url": "json/language/0009.json"
      },
      "short_effect": "Has an increased chance for a critical hit."
    }
  ],
  "flavor_text_entries": [
    {
      "flavor_text": "用大钳子\n敲打对手进行攻击。\n容易击中要害。",
      "language": {
        "name": "zh-Hans",
        "url": "json/language/0012.json"
      },
      "version_group": {
        "name": "ultra-sun-ultra-moon",
        "url": "json/version-group/0018.json"
      }
    },
    {
      "flavor_text": "大きな　ハサミを\n相手に　たたきつけて　攻撃する。\n急所に　当たりやすい。",
      "language": {
        "name": "ja",
        "url": "json/language/0011.json"
      },
      "version_group": {
        "name": "ultra-sun-ultra-moon",
        "url": "json/version-group/0018.json"
      }
    },
    {
      "flavor_text": "The target is hammered with a large pincer. Critical\nhits land more easily.",
      "language": {
        "name": "en",
        "url": "json/language/0009.json"
      },
      "version_group": {
        "name": "ultra-sun-ultra-moon",
        "url": "json/version-group/0018.json"
      }
    },
    {
      "flavor_text": "Danneggia il bersaglio servendosi di una grande\ntenaglia. Probabile brutto colpo.",
      "language": {
        "name": "it",
        "url": "json/language/0008.json"
      },
      "version_group": {
        "name": "ultra-sun-ultra-moon",
        "url": "json/version-group/0018.json"
      }
    },
    {
      "flavor_text": "Golpea con fuerza con una pinza enorme.\nSuele ser crítico.",
      "language": {
        "name": "es",
        "url": "json/language/0007.json"
      },
      "version_group": {
        "name": "ultra-sun-ultra-moon",
        "url": "json/version-group/0018.json"
      }
    },
    {
      "flavor_text": "Schlägt mit Schere zu. Hohe Volltrefferquote.",
      "language": {
        "name": "de",
        "url": "json/language/0006.json"
      },
      "version_group": {
        "name": "ultra-sun-ultra-moon",
        "url": "json/version-group/0018.json"
      }
    },
    {
      "flavor_text": "Une grande pince martèle l’ennemi.\nTaux de critique élevé.",
      "language": {
        "name": "fr",
        "url": "json/language/0005.json"
      },
      "version_group": {
        "name": "ultra-sun-ultra-moon",
        "url": "json/version-group/0018.json"
      }
    },
    {
      "flavor_text": "用巨大的鉗子\n敲打對手進行攻擊。\n容易擊中要害。",
      "language": {
        "name": "zh-Hant",
        "url": "json/language/0004.json"
      },
      "version_group": {
        "name": "ultra-sun-ultra-moon",
        "url": "json/version-group/0018.json"
      }
    },
    {
      "flavor_text": "큰 집게를\n상대에게 내리쳐서 공격한다.\n급소에 맞기 쉽다.",
      "language": {
        "name": "ko",
        "url": "json/language/0003.json"
      },
      "version_group": {
        "name": "ultra-sun-ultra-moon",
        "url": "json/version-group/0018.json"
      }
    },
    {
      "flavor_text": "おおきな　ハサミを\nあいてに　たたきつけて　こうげきする。\nきゅうしょに　あたりやすい。",
      "language": {
        "name": "ja-Hrkt",
        "url": "json/language/0001.json"
      },
      "version_group": {
        "name": "ultra-sun-ultra-moon",
        "url": "json/version-group/0018.json"
      }
    },
    {
      "flavor_text": "用大钳子\n敲打对手进行攻击。\n容易击中要害。",
      "language": {
        "name": "zh-Hans",
        "url": "json/language/0012.json"
      },
      "version_group": {
        "name": "sun-moon",
        "url": "json/version-group/0017.json"
      }
    },
    {
      "flavor_text": "大きな　ハサミを\n相手に　たたきつけて　攻撃する。\n急所に　当たりやすい。",
      "language": {
        "name": "ja",
        "url": "json/language/0011.json"
      },
      "version_group": {
        "name": "sun-moon",
        "url": "json/version-group/0017.json"
      }
    },
    {
      "flavor_text": "The target is hammered with a large pincer. Critical\nhits land more easily.",
      "language": {
        "name": "en",
        "url": "json/language/0009.json"
      },
      "version_group": {
        "name": "sun-moon",
        "url": "json/version-group/0017.json"
      }
    },
    {
      "flavor_text": "Danneggia il bersaglio servendosi di una grande\ntenaglia. Probabile brutto colpo.",
      "language": {
        "name": "it",
        "url": "json/language/0008.json"
      },
      "version_group": {
        "name": "sun-moon",
        "url": "json/version-group/0017.json"
      }
    },
    {
      "flavor_text": "Golpea con fuerza con una pinza enorme.\nSuele ser crítico.",
      "language": {
        "name": "es",
        "url": "json/language/0007.json"
      },
      "version_group": {
        "name": "sun-moon",
        "url": "json/version-group/0017.json"
      }
    },
    {
      "flavor_text": "Schlägt mit Schere zu. Hohe Volltrefferquote.",
      "language": {
        "name": "de",
        "url": "json/language/0006.json"
      },
      "version_group": {
        "name": "sun-moon",
        "url": "json/version-group/0017.json"
      }
    },
    {
      "flavor_text": "Une grande pince martèle l’ennemi.\nTaux de critique élevé.",
      "language": {
        "name": "fr",
        "url": "json/language/0005.json"
      },
      "version_group": {
        "name": "sun-moon",
        "url": "json/version-group/0017.json"
      }
    },
    {
      "flavor_text": "用巨大的鉗子\n敲打對手進行攻擊。\n容易擊中要害。",
      "language": {
        "name": "zh-Hant",
        "url": "json/language/0004.json"
      },
      "version_group": {
        "name": "sun-moon",
        "url": "json/version-group/0017.json"
      }
    },
    {
      "flavor_text": "큰 집게를\n상대에게 내리쳐서 공격한다.\n급소에 맞기 쉽다.",
      "language": {
        "name": "ko",
        "url": "json/language/0003.json"
      },
      "version_group": {
        "name": "sun-moon",
        "url": "json/version-group/0017.json"
      }
    },
    {
      "flavor_text": "おおきな　ハサミを\nあいてに　たたきつけて　こうげきする。\nきゅうしょに　あたりやすい。",
      "language": {
        "name": "ja-Hrkt",
        "url": "json/language/0001.json"
      },
      "version_group": {
        "name": "sun-moon",
        "url": "json/version-group/0017.json"
      }
    },
    {
      "flavor_text": "大きな　ハサミを\n相手に　たたきつけて　攻撃する。\n急所に　当たりやすい。",
      "language": {
        "name": "ja",
        "url": "json/language/0011.json"
      },
      "version_group": {
        "name": "omega-ruby-alpha-sapphire",
        "url": "json/version-group/0016.json"
      }
    },
    {
      "flavor_text": "The target is hammered with a large pincer.\nCritical hits land more easily.",
      "language": {
        "name": "en",
        "url": "json/language/0009.json"
      },
      "version_group": {
        "name": "omega-ruby-alpha-sapphire",
        "url": "json/version-group/0016.json"
      }
    },
    {
      "flavor_text": "Danneggia il bersaglio servendosi di una grande\ntenaglia. Probabile brutto colpo.",
      "language": {
        "name": "it",
        "url": "json/language/0008.json"
      },
      "version_group": {
        "name": "omega-ruby-alpha-sapphire",
        "url": "json/version-group/0016.json"
      }
    },
    {
      "flavor_text": "Golpea con fuerza con una pinza enorme.\nSuele ser crítico.",
      "language": {
        "name": "es",
        "url": "json/language/0007.json"
      },
      "version_group": {
        "name": "omega-ruby-alpha-sapphire",
        "url": "json/version-group/0016.json"
      }
    },
    {
      "flavor_text": "Schlägt mit Schere zu. Hohe Volltrefferquote.",
      "language": {
        "name": "de",
        "url": "json/language/0006.json"
      },
      "version_group": {
        "name": "omega-ruby-alpha-sapphire",
        "url": "json/version-group/0016.json"
      }
    },
    {
      "flavor_text": "Une grande pince martèle l’ennemi.\nTaux de critiques élevé.",
      "language": {
        "name": "fr",
        "url": "json/language/0005.json"
      },
      "version_group": {
        "name": "omega-ruby-alpha-sapphire",
        "url": "json/version-group/0016.json"
      }
    },
    {
      "flavor_text": "큰 집게를\n상대에게 내리쳐서 공격한다.\n급소에 맞기 쉽다.",
      "language": {
        "name": "ko",
        "url": "json/language/0003.json"
      },
      "version_group": {
        "name": "omega-ruby-alpha-sapphire",
        "url": "json/version-group/0016.json"
      }
    },
    {
      "flavor_text": "おおきな　ハサミを\nあいてに　たたきつけて　こうげきする。\nきゅうしょに　あたりやすい。",
      "language": {
        "name": "ja-Hrkt",
        "url": "json/language/0001.json"
      },
      "version_group": {
        "name": "omega-ruby-alpha-sapphire",
        "url": "json/version-group/0016.json"
      }
    },
    {
      "flavor_text": "大きな　ハサミを\n相手に　たたきつけて　攻撃する。\n急所に　当たりやすい。",
      "language": {
        "name": "ja",
        "url": "json/language/0011.json"
      },
      "version_group": {
        "name": "x-y",
        "url": "json/version-group/0015.json"
      }
    },
    {
      "flavor_text": "The target is hammered with a large pincer.\nCritical hits land more easily.",
      "language": {
        "name": "en",
        "url": "json/language/0009.json"
      },
      "version_group": {
        "name": "x-y",
        "url": "json/version-group/0015.json"
      }
    },
    {
      "flavor_text": "Danneggia il bersaglio servendosi di una grande\ntenaglia. Probabile brutto colpo.",
      "language": {
        "name": "it",
        "url": "json/language/0008.json"
      },
      "version_group": {
        "name": "x-y",
        "url": "json/version-group/0015.json"
      }
    },
    {
      "flavor_text": "Golpea con fuerza con una pinza enorme.\nSuele ser crítico.",
      "language": {
        "name": "es",
        "url": "json/language/0007.json"
      },
      "version_group": {
        "name": "x-y",
        "url": "json/version-group/0015.json"
      }
    },
    {
      "flavor_text": "Schlägt mit Schere zu. Hohe Volltrefferquote.",
      "language": {
        "name": "de",
        "url": "json/language/0006.json"
      },
      "version_group": {
        "name": "x-y",
        "url": "json/version-group/0015.json"
      }
    },
    {
      "flavor_text": "Une grande pince martèle l’ennemi.\nTaux de critiques élevé.",
      "language": {
        "name": "fr",
        "url": "json/language/0005.json"
      },
      "version_group": {
        "name": "x-y",
        "url": "json/version-group/0015.json"
      }
    },
    {
      "flavor_text": "큰 집게를\n상대에게 내리쳐서 공격한다.\n급소에 맞기 쉽다.",
      "language": {
        "name": "ko",
        "url": "json/language/0003.json"
      },
      "version_group": {
        "name": "x-y",
        "url": "json/version-group/0015.json"
      }
    },
    {
      "flavor_text": "おおきな　ハサミを\nあいてに　たたきつけて　こうげきする。\nきゅうしょに　あたりやすい。",
      "language": {
        "name": "ja-Hrkt",
        "url": "json/language/0001.json"
      },
      "version_group": {
        "name": "x-y",
        "url": "json/version-group/0015.json"
      }
    },
    {
      "flavor_text": "The target is hammered with a large pincer.\nCritical hits land more easily.",
      "language": {
        "name": "en",
        "url": "json/language/0009.json"
      },
      "version_group": {
        "name": "black-2-white-2",
        "url": "json/version-group/0014.json"
      }
    },
    {
      "flavor_text": "The target is hammered with a large pincer.\nCritical hits land more easily.",
      "language": {
        "name": "en",
        "url": "json/language/0009.json"
      },
      "version_group": {
        "name": "black-white",
        "url": "json/version-group/0011.json"
      }
    },
    {
      "flavor_text": "Une grande pince martèle l’ennemi.\nTaux de critiques élevé.",
      "language": {
        "name": "fr",
        "url": "json/language/0005.json"
      },
      "version_group": {
        "name": "black-white",
        "url": "json/version-group/0011.json"
      }
    },
    {
      "flavor_text": "The foe is hammered\nwith a large pincer.\nThis move has a high\ncritical-hit ratio.\n",
      "language": {
        "name": "en",
        "url": "json/language/0009.json"
      },
      "version_group": {
        "name": "heartgold-soulsilver",
        "url": "json/version-group/0010.json"
      }
    },
    {
      "flavor_text": "The foe is hammered\nwith a large pincer.\nThis move has a high\ncritical-hit ratio.\n",
      "language": {
        "name": "en",
        "url": "json/language/0009.json"
      },
      "version_group": {
        "name": "platinum",
        "url": "json/version-group/0009.json"
      }
    },
    {
      "flavor_text": "The foe is hammered\nwith a large pincer.\nThis move has a high\ncritical-hit ratio.\n",
      "language": {
        "name": "en",
        "url": "json/language/0009.json"
      },
      "version_group": {
        "name": "diamond-pearl",
        "url": "json/version-group/0008.json"
      }
    },
    {
      "flavor_text": "A large pincer is\nused to hammer the\nfoe. It has a high\ncritical-hit ratio.",
      "language": {
        "name": "en",
        "url": "json/language/0009.json"
      },
      "version_group": {
        "name": "firered-leafgreen",
        "url": "json/version-group/0007.json"
      }
    },
    {
      "flavor_text": "Hammers with a pincer. Has a\nhigh critical-hit ratio.",
      "language": {
        "name": "en",
        "url": "json/language/0009.json"
      },
      "version_group": {
        "name": "emerald",
        "url": "json/version-group/0006.json"
      }
    },
    {
      "flavor_text": "Hammers with a pincer. Has a\nhigh critical-hit ratio.",
      "language": {
        "name": "en",
        "url": "json/language/0009.json"
      },
      "version_group": {
        "name": "ruby-sapphire",
        "url": "json/version-group/0005.json"
      }
    },
    {
      "flavor_text": "Has a high criti­\ncal hit ratio.",
      "language": {
        "name": "en",
        "url": "json/language/0009.json"
      },
      "version_group": {
        "name": "crystal",
        "url": "json/version-group/0004.json"
      }
    },
    {
      "flavor_text": "Has a high criti­\ncal hit ratio.",
      "language": {
        "name": "en",
        "url": "json/language/0009.json"
      },
      "version_group": {
        "name": "gold-silver",
        "url": "json/version-group/0003.json"
      }
    }
  ],
  "generation": {
    "name": "generation-i",
    "url": "json/generation/0001.json"
  },
  "id": 152,
  "machines": [],
  "meta": {
    "ailment": {
      "name": "none",
      "url": "json/move-ailment/0000.json"
    },
    "ailment_chance": 0,
    "category": {
      "name": "damage",
      "url": "json/move-category/0000.json"
    },
    "crit_rate": 1,
    "drain": 0,
    "flinch_chance": 0,
    "healing": 0,
    "max_hits": null,
    "max_turns": null,
    "min_hits": null,
    "min_turns": null,
    "stat_chance": 0
  },
  "name": "crabhammer",
  "names": [
    {
      "language": {
        "name": "zh-Hans",
        "url": "json/language/0012.json"
      },
      "name": "蟹钳锤"
    },
    {
      "language": {
        "name": "ja",
        "url": "json/language/0011.json"
      },
      "name": "クラブハンマー"
    },
    {
      "language": {
        "name": "en",
        "url": "json/language/0009.json"
      },
      "name": "Crabhammer"
    },
    {
      "language": {
        "name": "it",
        "url": "json/language/0008.json"
      },
      "name": "Martellata"
    },
    {
      "language": {
        "name": "es",
        "url": "json/language/0007.json"
      },
      "name": "Martillazo"
    },
    {
      "language": {
        "name": "de",
        "url": "json/language/0006.json"
      },
      "name": "Krabbhammer"
    },
    {
      "language": {
        "name": "fr",
        "url": "json/language/0005.json"
      },
      "name": "Pince-Masse"
    },
    {
      "language": {
        "name": "zh-Hant",
        "url": "json/language/0004.json"
      },
      "name": "蟹鉗錘"
    },
    {
      "language": {
        "name": "ko",
        "url": "json/language/0003.json"
      },
      "name": "찝게햄머"
    },
    {
      "language": {
        "name": "ja-Hrkt",
        "url": "json/language/0001.json"
      },
      "name": "クラブハンマー"
    }
  ],
  "past_values": [
    {
      "accuracy": 85,
      "effect_chance": null,
      "effect_entries": [],
      "power": null,
      "pp": null,
      "type": null,
      "version_group": {
        "name": "black-white",
        "url": "json/version-group/0011.json"
      }
    },
    {
      "accuracy": null,
      "effect_chance": null,
      "effect_entries": [],
      "power": 90,
      "pp": null,
      "type": null,
      "version_group": {
        "name": "x-y",
        "url": "json/version-group/0015.json"
      }
    }
  ],
  "power": 100,
  "pp": 10,
  "priority": 0,
  "stat_changes": [],
  "super_contest_effect": {
    "url": "json/super-contest-effect/0018.json"
  },
  "target": {
    "name": "selected-pokemon",
    "url": "json/move-target/0010.json"
  },
  "type": {
    "name": "water",
    "url": "json/type/0011.json"
  }
}