{
  "accuracy": 100,
  "contest_combos": null,
  "contest_effect": null,
  "contest_type": null,
  "damage_class": {
    "name": "status",
    "url": "json/move-damage-class/0001.json"
  },
  "effect_chance": 100,
  "effect_changes": [],
  "effect_entries": [
    {
      "effect": "Poisons the target and lowers its Speed by one stage.",
      "language": {
        "name": "en",
        "url": "json/language/0009.json"
      },
      "short_effect": "Poisons the target and lowers its Speed by one stage."
    }
  ],
  "flavor_text_entries": [
    {
      "flavor_text": "将混有毒的丝吐向对手。\n使其中毒，\n从而降低对手的速度。",
      "language": {
        "name": "zh-Hans",
        "url": "json/language/0012.json"
      },
      "version_group": {
        "name": "ultra-sun-ultra-moon",
        "url": "json/version-group/0018.json"
      }
    },
    {
      "flavor_text": "毒の　混じった　糸を　吹き付ける。\n相手を　毒にして\n素早さを　さげる。",
      "language": {
        "name": "ja",
        "url": "json/language/0011.json"
      },
      "version_group": {
        "name": "ultra-sun-ultra-moon",
        "url": "json/version-group/0018.json"
      }
    },
    {
      "flavor_text": "The user shoots poisonous threads to poison the\ntarget and lower the target’s Speed stat.",
      "language": {
        "name": "en",
        "url": "json/language/0009.json"
      },
      "version_group": {
        "name": "ultra-sun-ultra-moon",
        "url": "json/version-group/0018.json"
      }
    },
    {
      "flavor_text": "Avvelena il bersaglio avvolgendolo con filamenti\ntossici e ne riduce la Velocità.",
      "language": {
        "name": "it",
        "url": "json/language/0008.json"
      },
      "version_group": {
        "name": "ultra-sun-ultra-moon",
        "url": "json/version-group/0018.json"
      }
    },
    {
      "flavor_text": "Ataca al oponente con hilillos venenosos que\nreducen su Velocidad y lo envenenan.",
      "language": {
        "name": "es",
        "url": "json/language/0007.json"
      },
      "version_group": {
        "name": "ultra-sun-ultra-moon",
        "url": "json/version-group/0018.json"
      }
    },
    {
      "flavor_text": "Der Anwender schießt giftige Fäden auf das Ziel,\ndas dadurch vergiftet wird. Außerdem sinkt seine\nInitiative.",
      "language": {
        "name": "de",
        "url": "json/language/0006.json"
      },
      "version_group": {
        "name": "ultra-sun-ultra-moon",
        "url": "json/version-group/0018.json"
      }
    },
    {
      "flavor_text": "Tisse un fil imprégné de venin. Empoisonne la cible\net baisse sa Vitesse.",
      "language": {
        "name": "fr",
        "url": "json/language/0005.json"
      },
      "version_group": {
        "name": "ultra-sun-ultra-moon",
        "url": "json/version-group/0018.json"
      }
    },
    {
      "flavor_text": "將混有毒的絲吐向對手。\n使其中毒，\n進而降低對手的速度。",
      "language": {
        "name": "zh-Hant",
        "url": "json/language/0004.json"
      },
      "version_group": {
        "name": "ultra-sun-ultra-moon",
        "url": "json/version-group/0018.json"
      }
    },
    {
      "flavor_text": "독이 섞인 실을 뿜어낸다.\n상대를 독 상태로 만들고\n스피드를 떨어뜨린다.",
      "language": {
        "name": "ko",
        "url": "json/language/0003.json"
      },
      "version_group": {
        "name": "ultra-sun-ultra-moon",
        "url": "json/version-group/0018.json"
      }
    },
    {
      "flavor_text": "どくの　まじった　いとを　ふきつける。\nあいてを　どくにして\nすばやさを　さげる。",
      "language": {
        "name": "ja-Hrkt",
        "url": "json/language/0001.json"
      },
      "version_group": {
        "name": "ultra-sun-ultra-moon",
        "url": "json/version-group/0018.json"
      }
    },
    {
      "flavor_text": "将混有毒的丝吐向对手。\n使其中毒，\n从而降低对手的速度。",
      "language": {
        "name": "zh-Hans",
        "url": "json/language/0012.json"
      },
      "version_group": {
        "name": "sun-moon",
        "url": "json/version-group/0017.json"
      }
    },
    {
      "flavor_text": "毒の　混じった　糸を　吹き付ける。\n相手を　毒にして\n素早さを　さげる。",
      "language": {
        "name": "ja",
        "url": "json/language/0011.json"
      },
      "version_group": {
        "name": "sun-moon",
        "url": "json/version-group/0017.json"
      }
    },
    {
      "flavor_text": "The user shoots poisonous threads to poison the\ntarget and lower the target’s Speed stat.",
      "language": {
        "name": "en",
        "url": "json/language/0009.json"
      },
      "version_group": {
        "name": "sun-moon",
        "url": "json/version-group/0017.json"
      }
    },
    {
      "flavor_text": "Avvelena il bersaglio avvolgendolo con filamenti\ntossici e ne riduce la Velocità.",
      "language": {
        "name": "it",
        "url": "json/language/0008.json"
      },
      "version_group": {
        "name": "sun-moon",
        "url": "json/version-group/0017.json"
      }
    },
    {
      "flavor_text": "Ataca al oponente con hilillos venenosos que\nreducen su Velocidad y lo envenenan.",
      "language": {
        "name": "es",
        "url": "json/language/0007.json"
      },
      "version_group": {
        "name": "sun-moon",
        "url": "json/version-group/0017.json"
      }
    },
    {
      "flavor_text": "Der Anwender schießt giftige Fäden auf das Ziel,\ndas dadurch vergiftet wird. Außerdem sinkt seine\nInitiative.",
      "language": {
        "name": "de",
        "url": "json/language/0006.json"
      },
      "version_group": {
        "name": "sun-moon",
        "url": "json/version-group/0017.json"
      }
    },
    {
      "flavor_text": "Tisse un fil imprégné de venin. Empoisonne la cible\net baisse sa Vitesse.",
      "language": {
        "name": "fr",
        "url": "json/language/0005.json"
      },
      "version_group": {
        "name": "sun-moon",
        "url": "json/version-group/0017.json"
      }
    },
    {
      "flavor_text": "將混有毒的絲吐向對手。\n使其中毒，\n進而降低對手的速度。",
      "language": {
        "name": "zh-Hant",
        "url": "json/language/0004.json"
      },
      "version_group": {
        "name": "sun-moon",
        "url": "json/version-group/0017.json"
      }
    },
    {
      "flavor_text": "독이 섞인 실을 뿜어낸다.\n상대를 독 상태로 만들고\n스피드를 떨어뜨린다.",
      "language": {
        "name": "ko",
        "url": "json/language/0003.json"
      },
      "version_group": {
        "name": "sun-moon",
        "url": "json/version-group/0017.json"
      }
    },
    {
      "flavor_text": "どくの　まじった　いとを　ふきつける。\nあいてを　どくにして\nすばやさを　さげる。",
      "language": {
        "name": "ja-Hrkt",
        "url": "json/language/0001.json"
      },
      "version_group": {
        "name": "sun-moon",
        "url": "json/version-group/0017.json"
      }
    }
  ],
  "generation": {
    "name": "generation-vii",
    "url": "json/generation/0007.json"
  },
  "id": 672,
  "machines": [],
  "meta": {
    "ailment": {
      "name": "poison",
      "url": "json/move-ailment/0005.json"
    },
    "ailment_chance": 100,
    "category": {
      "name": "swagger",
      "url": "json/move-category/0005.json"
    },
    "crit_rate": 0,
    "drain": 0,
    "flinch_chance": 0,
    "healing": 0,
    "max_hits": null,
    "max_turns": null,
    "min_hits": null,
    "min_turns": null,
    "stat_chance": 0
  },
  "name": "toxic-thread",
  "names": [
    {
      "language": {
        "name": "zh-Hans",
        "url": "json/language/0012.json"
      },
      "name": "毒丝"
    },
    {
      "language": {
        "name": "ja",
        "url": "json/language/0011.json"
      },
      "name": "どくのいと"
    },
    {
      "language": {
        "name": "en",
        "url": "json/language/0009.json"
      },
      "name": "Toxic Thread"
    },
    {
      "language": {
        "name": "it",
        "url": "json/language/0008.json"
      },
      "name": "Velenotela"
    },
    {
      "language": {
        "name": "es",
        "url": "json/language/0007.json"
      },
      "name": "Hilo Venenoso"
    },
    {
      "language": {
        "name": "de",
        "url": "json/language/0006.json"
      },
      "name": "Giftfaden"
    },
    {
      "language": {
        "name": "fr",
        "url": "json/language/0005.json"
      },
      "name": "Fil Toxique"
    },
    {
      "language": {
        "name": "zh-Hant",
        "url": "json/language/0004.json"
      },
      "name": "毒絲"
    },
    {
      "language": {
        "name": "ko",
        "url": "json/language/0003.json"
      },
      "name": "독실"
    },
    {
      "language": {
        "name": "ja-Hrkt",
        "url": "json/language/0001.json"
      },
      "name": "どくのいと"
    }
  ],
  "past_values": [],
  "power": null,
  "pp": 20,
  "priority": 0,
  "stat_changes": [],
  "super_contest_effect": null,
  "target": {
    "name": "selected-pokemon",
    "url": "json/move-target/0010.json"
  },
  "type": {
    "name": "poison",
    "url": "json/type/0004.json"
  }
}