{
  "areas": [
    {
      "name": "green-path-area",
      "url": "json/location-area/0522.json"
    }
  ],
  "game_indices": [],
  "id": 515,
  "name": "green-path",
  "names": [
    {
      "language": {
        "name": "en",
        "url": "json/language/0009.json"
      },
      "name": "Green Path"
    },
    {
      "language": {
        "name": "fr",
        "url": "json/language/0005.json"
      },
      "name": "Chemin Vert"
    }
  ],
  "region": {
    "name": "kanto",
    "url": "json/region/0001.json"
  }
}